whenever_time_period/__init__.py
whenever_time_period/abstract.py
whenever_time_period/time_period.py
whenever_time_period-0.0.2.dist-info/LICENSE.txt
whenever_time_period-0.0.2.dist-info/METADATA
whenever_time_period-0.0.2.dist-info/WHEEL
whenever_time_period-0.0.2.dist-info/top_level.txt
whenever_time_period-0.0.2.dist-info/RECORD
