Metadata-Version: 2.1
Name: whenever_time_period
Version: 0.0.2
Summary: Unofficial support for time periods in whenever
Project-URL: Homepage, https://github.com/Ecaloota/whenever_time_period
Project-URL: Issues, https://github.com/Ecaloota/whenever_time_period/issues
Classifier: Programming Language :: Python :: 3
Classifier: Operating System :: OS Independent
Requires-Python: >=3.12
License-File: LICENSE.txt
